Metadata-Version: 1.1
Name: Geometry2D
Version: 0.1
Summary: This is a library for creating and manipulating 2D Geometric Shapes
Home-page: https://github.com/circleshavecorners/Geometry2D
Author: Ron Rivest
Author-email: ron.rivest@gmail.com
License: MIT
Download-URL: https://github.com/circleshavecorners/Geometry2D/archive/v_01.tar.gz
Platform: UNKNOWN
Classifier: Development Status :: 3 - Alpha
Classifier: Intended Audience :: Developers
Classifier: Topic :: Software Development :: Build Tools
Classifier: License :: OSI Approved :: MIT License
Classifier: Programming Language :: Python :: 3
Classifier: Programming Language :: Python :: 3.4
Classifier: Programming Language :: Python :: 3.5
Classifier: Programming Language :: Python :: 3.6
